[
    {
        "actual_preview_height": 300,
        "actual_preview_width": 150,
        "approver_id": null,
        "author": "Genex",
        "change": 5709158,
        "created_at": 1698345929,
        "creator_id": 178012,
        "file_ext": "jpg",
        "file_size": 12210485,
        "file_url": "https://files.yande.re/image/e42915252258907ebaa982aa0ae3ffe2/yande.re%201128895%20azur_lane%20bismarck_%28azur_lane%29%20cramcell%20garter%20pantyhose%20seifuku.jpg",
        "frames": [],
        "frames_pending": [],
        "frames_pending_string": "",
        "frames_string": "",
        "has_children": false,
        "height": 7082,
        "id": 1128895,
        "is_held": false,
        "is_note_locked": false,
        "is_pending": false,
        "is_rating_locked": false,
        "is_shown_in_index": true,
        "jpeg_file_size": 0,
        "jpeg_height": 7082,
        "jpeg_url": "https://files.yande.re/image/e42915252258907ebaa982aa0ae3ffe2/yande.re%201128895%20azur_lane%20bismarck_%28azur_lane%29%20cramcell%20garter%20pantyhose%20seifuku.jpg",
        "jpeg_width": 3541,
        "last_commented_at": 0,
        "last_noted_at": 0,
        "md5": "e42915252258907ebaa982aa0ae3ffe2",
        "parent_id": null,
        "preview_height": 150,
        "preview_url": "https://assets.yande.re/data/preview/e4/29/e42915252258907ebaa982aa0ae3ffe2.jpg",
        "preview_width": 75,
        "rating": "s",
        "sample_file_size": 259383,
        "sample_height": 1500,
        "sample_url": "https://files.yande.re/sample/e42915252258907ebaa982aa0ae3ffe2/yande.re%201128895%20sample%20azur_lane%20bismarck_%28azur_lane%29%20cramcell%20garter%20pantyhose%20seifuku.jpg",
        "sample_width": 750,
        "score": 19,
        "source": "",
        "status": "active",
        "tags": "azur_lane bismarck_(azur_lane) cramcell garter pantyhose seifuku",
        "updated_at": 1698345929,
        "width": 3541
    },
    {
        "actual_preview_height": 300,
        "actual_preview_width": 207,
        "approver_id": null,
        "author": "Genex",
        "change": 5709152,
        "created_at": 1698344231,
        "creator_id": 178012,
        "file_ext": "png",
        "file_size": 2472908,
        "file_url": "https://files.yande.re/image/124d1b5c1b640ade5d55f4ea71224d63/yande.re%201128893%20ass%20azur_lane%20bismarck_%28azur_lane%29%20cramcell%20dress%20no_bra.png",
        "frames": [],
        "frames_pending": [],
        "frames_pending_string": "",
        "frames_string": "",
        "has_children": false,
        "height": 2000,
        "id": 1128893,
        "is_held": false,
        "is_note_locked": false,
        "is_pending": false,
        "is_rating_locked": false,
        "is_shown_in_index": true,
        "jpeg_file_size": 322488,
        "jpeg_height": 2000,
        "jpeg_url": "https://files.yande.re/jpeg/124d1b5c1b640ade5d55f4ea71224d63/yande.re%201128893%20ass%20azur_lane%20bismarck_%28azur_lane%29%20cramcell%20dress%20no_bra.jpg",
        "jpeg_width": 1377,
        "last_commented_at": 0,
        "last_noted_at": 0,
        "md5": "124d1b5c1b640ade5d55f4ea71224d63",
        "parent_id": null,
        "preview_height": 150,
        "preview_url": "https://assets.yande.re/data/preview/12/4d/124d1b5c1b640ade5d55f4ea71224d63.jpg",
        "preview_width": 103,
        "rating": "s",
        "sample_file_size": 160858,
        "sample_height": 1500,
        "sample_url": "https://files.yande.re/sample/124d1b5c1b640ade5d55f4ea71224d63/yande.re%201128893%20sample%20ass%20azur_lane%20bismarck_%28azur_lane%29%20cramcell%20dress%20no_bra.jpg",
        "sample_width": 1033,
        "score": 14,
        "source": "https://i.pximg.net/img-original/img/2023/10/20/00/00/13/112686284_p0.png",
        "status": "active",
        "tags": "ass azur_lane bismarck_(azur_lane) cramcell dress no_bra",
        "updated_at": 1698344403,
        "width": 1377
    },
    {
        "actual_preview_height": 229,
        "actual_preview_width": 300,
        "approver_id": null,
        "author": "TheXoNs",
        "change": 5709286,
        "created_at": 1698328423,
        "creator_id": 349224,
        "file_ext": "png",
        "file_size": 3059236,
        "file_url": "https://files.yande.re/image/a4afe4214b0a3834a5ec7c7375f188d7/yande.re%201128861%20azur_lane%20devil%20halloween%20heels%20pointy_ears%20stockings%20tagme%20thighhighs%20transparent_png%20wings%20z24_%28azur_lane%29.png",
        "frames": [],
        "frames_pending": [],
        "frames_pending_string": "",
        "frames_string": "",
        "has_children": false,
        "height": 1566,
        "id": 1128861,
        "is_held": false,
        "is_note_locked": false,
        "is_pending": false,
        "is_rating_locked": false,
        "is_shown_in_index": true,
        "jpeg_file_size": 620564,
        "jpeg_height": 1566,
        "jpeg_url": "https://files.yande.re/jpeg/a4afe4214b0a3834a5ec7c7375f188d7/yande.re%201128861%20azur_lane%20devil%20halloween%20heels%20pointy_ears%20stockings%20tagme%20thighhighs%20transparent_png%20wings%20z24_%28azur_lane%29.jpg",
        "jpeg_width": 2048,
        "last_commented_at": 0,
        "last_noted_at": 0,
        "md5": "a4afe4214b0a3834a5ec7c7375f188d7",
        "parent_id": null,
        "preview_height": 115,
        "preview_url": "https://assets.yande.re/data/preview/a4/af/a4afe4214b0a3834a5ec7c7375f188d7.jpg",
        "preview_width": 150,
        "rating": "s",
        "sample_file_size": 298699,
        "sample_height": 1147,
        "sample_url": "https://files.yande.re/sample/a4afe4214b0a3834a5ec7c7375f188d7/yande.re%201128861%20sample%20azur_lane%20devil%20halloween%20heels%20pointy_ears%20stockings%20tagme%20thighhighs%20transparent_png%20wings%20z24_%28azur_lane%29.jpg",
        "sample_width": 1500,
        "score": 28,
        "source": "",
        "status": "active",
        "tags": "azur_lane devil halloween heels pointy_ears stockings tagme thighhighs transparent_png wings z24_(azur_lane)",
        "updated_at": 1698328423,
        "width": 2048
    },
    {
        "actual_preview_height": 300,
        "actual_preview_width": 295,
        "approver_id": null,
        "author": "BattlequeenYume",
        "change": 5709283,
        "created_at": 1698328233,
        "creator_id": 323282,
        "file_ext": "png",
        "file_size": 3721141,
        "file_url": "https://files.yande.re/image/1594a785caaffd58e34141369e05c77b/yande.re%201128858%20azur_lane%20tagme%20victorious_%28azur_lane%29%20yukata.png",
        "frames": [],
        "frames_pending": [],
        "frames_pending_string": "",
        "frames_string": "",
        "has_children": false,
        "height": 2016,
        "id": 1128858,
        "is_held": false,
        "is_note_locked": false,
        "is_pending": false,
        "is_rating_locked": false,
        "is_shown_in_index": true,
        "jpeg_file_size": 752027,
        "jpeg_height": 2016,
        "jpeg_url": "https://files.yande.re/jpeg/1594a785caaffd58e34141369e05c77b/yande.re%201128858%20azur_lane%20tagme%20victorious_%28azur_lane%29%20yukata.jpg",
        "jpeg_width": 1980,
        "last_commented_at": 0,
        "last_noted_at": 0,
        "md5": "1594a785caaffd58e34141369e05c77b",
        "parent_id": null,
        "preview_height": 150,
        "preview_url": "https://assets.yande.re/data/preview/15/94/1594a785caaffd58e34141369e05c77b.jpg",
        "preview_width": 147,
        "rating": "s",
        "sample_file_size": 271352,
        "sample_height": 1222,
        "sample_url": "https://files.yande.re/sample/1594a785caaffd58e34141369e05c77b/yande.re%201128858%20sample%20azur_lane%20tagme%20victorious_%28azur_lane%29%20yukata.jpg",
        "sample_width": 1200,
        "score": 20,
        "source": "",
        "status": "active",
        "tags": "azur_lane tagme victorious_(azur_lane) yukata",
        "updated_at": 1698354538,
        "width": 1980
    }
]