[
    {
        "actual_preview_height": 300,
        "actual_preview_width": 208,
        "approver_id": 11598,
        "author": "dhzzang4339",
        "change": 5674116,
        "created_at": 1695051833,
        "creator_id": 500508,
        "file_ext": "jpg",
        "file_size": 395254,
        "file_url": "https://files.yande.re/image/d3456c969c1e5ce70d7dc20b3641ae43/yande.re%201121109%20animal_ears%20hoto_cocoa%20jouga_maya%20kafuu_chino%20kirima_sharo%20natsu_megumi%20nekomimi%20pantyhose%20tagme%20tedeza_rize%20ujimatsu_chiya.jpg",
        "frames": [],
        "frames_pending": [],
        "frames_pending_string": "",
        "frames_string": "",
        "has_children": false,
        "height": 1558,
        "id": 1121109,
        "is_held": false,
        "is_note_locked": false,
        "is_pending": false,
        "is_rating_locked": false,
        "is_shown_in_index": true,
        "jpeg_file_size": 0,
        "jpeg_height": 1558,
        "jpeg_url": "https://files.yande.re/image/d3456c969c1e5ce70d7dc20b3641ae43/yande.re%201121109%20animal_ears%20hoto_cocoa%20jouga_maya%20kafuu_chino%20kirima_sharo%20natsu_megumi%20nekomimi%20pantyhose%20tagme%20tedeza_rize%20ujimatsu_chiya.jpg",
        "jpeg_width": 1081,
        "last_commented_at": 0,
        "last_noted_at": 0,
        "md5": "d3456c969c1e5ce70d7dc20b3641ae43",
        "parent_id": null,
        "preview_height": 150,
        "preview_url": "https://assets.yande.re/data/preview/d3/45/d3456c969c1e5ce70d7dc20b3641ae43.jpg",
        "preview_width": 104,
        "rating": "q",
        "sample_file_size": 509970,
        "sample_height": 1500,
        "sample_url": "https://files.yande.re/sample/d3456c969c1e5ce70d7dc20b3641ae43/yande.re%201121109%20sample%20animal_ears%20hoto_cocoa%20jouga_maya%20kafuu_chino%20kirima_sharo%20natsu_megumi%20nekomimi%20pantyhose%20tagme%20tedeza_rize%20ujimatsu_chiya.jpg",
        "sample_width": 1041,
        "score": 13,
        "source": "https://twitter.com/NANANA923531402/status/1703795094854508585",
        "status": "active",
        "tags": "animal_ears gochuumon_wa_usagi_desu_ka? hoto_cocoa jouga_maya kafuu_chino kirima_sharo natsu_megumi nekomimi pantyhose tagme tedeza_rize ujimatsu_chiya",
        "updated_at": 1695157304,
        "width": 1081
    },
    {
        "actual_preview_height": 300,
        "actual_preview_width": 210,
        "approver_id": null,
        "author": "Lzhom",
        "change": 5663166,
        "created_at": 1694199428,
        "creator_id": 513205,
        "file_ext": "png",
        "file_size": 4042857,
        "file_url": "https://files.yande.re/image/ffc8269f672910f16df2c5095bb5db51/yande.re%201119037%20gochuumon_wa_usagi_desu_ka%3F%20hoto_cocoa%20naked%20nipples%20tooo%20ujimatsu_chiya%20yuri.png",
        "frames": [],
        "frames_pending": [],
        "frames_pending_string": "",
        "frames_string": "",
        "has_children": false,
        "height": 2732,
        "id": 1119037,
        "is_held": false,
        "is_note_locked": false,
        "is_pending": false,
        "is_rating_locked": false,
        "is_shown_in_index": true,
        "jpeg_file_size": 960721,
        "jpeg_height": 2732,
        "jpeg_url": "https://files.yande.re/jpeg/ffc8269f672910f16df2c5095bb5db51/yande.re%201119037%20gochuumon_wa_usagi_desu_ka%3F%20hoto_cocoa%20naked%20nipples%20tooo%20ujimatsu_chiya%20yuri.jpg",
        "jpeg_width": 1912,
        "last_commented_at": 0,
        "last_noted_at": 0,
        "md5": "ffc8269f672910f16df2c5095bb5db51",
        "parent_id": null,
        "preview_height": 150,
        "preview_url": "https://assets.yande.re/data/preview/ff/c8/ffc8269f672910f16df2c5095bb5db51.jpg",
        "preview_width": 105,
        "rating": "q",
        "sample_file_size": 319018,
        "sample_height": 1500,
        "sample_url": "https://files.yande.re/sample/ffc8269f672910f16df2c5095bb5db51/yande.re%201119037%20sample%20gochuumon_wa_usagi_desu_ka%3F%20hoto_cocoa%20naked%20nipples%20tooo%20ujimatsu_chiya%20yuri.jpg",
        "sample_width": 1050,
        "score": 27,
        "source": "",
        "status": "active",
        "tags": "gochuumon_wa_usagi_desu_ka? hoto_cocoa naked nipples tooo ujimatsu_chiya yuri",
        "updated_at": 1694228225,
        "width": 1912
    },
    {
        "actual_preview_height": 221,
        "actual_preview_width": 300,
        "approver_id": null,
        "author": "dhzzang4339",
        "change": 5655170,
        "created_at": 1693716044,
        "creator_id": 500508,
        "file_ext": "jpg",
        "file_size": 418873,
        "file_url": "https://files.yande.re/image/c6b1ade57be213eaf77f67dbe8874278/yande.re%201117669%20gochuumon_wa_usagi_desu_ka%3F%20hoto_cocoa%20koi%20seifuku%20ujimatsu_chiya.jpg",
        "frames": [],
        "frames_pending": [],
        "frames_pending_string": "",
        "frames_string": "",
        "has_children": false,
        "height": 1491,
        "id": 1117669,
        "is_held": false,
        "is_note_locked": false,
        "is_pending": false,
        "is_rating_locked": false,
        "is_shown_in_index": true,
        "jpeg_file_size": 0,
        "jpeg_height": 1491,
        "jpeg_url": "https://files.yande.re/image/c6b1ade57be213eaf77f67dbe8874278/yande.re%201117669%20gochuumon_wa_usagi_desu_ka%3F%20hoto_cocoa%20koi%20seifuku%20ujimatsu_chiya.jpg",
        "jpeg_width": 2024,
        "last_commented_at": 0,
        "last_noted_at": 0,
        "md5": "c6b1ade57be213eaf77f67dbe8874278",
        "parent_id": null,
        "preview_height": 110,
        "preview_url": "https://assets.yande.re/data/preview/c6/b1/c6b1ade57be213eaf77f67dbe8874278.jpg",
        "preview_width": 150,
        "rating": "q",
        "sample_file_size": 399210,
        "sample_height": 1105,
        "sample_url": "https://files.yande.re/sample/c6b1ade57be213eaf77f67dbe8874278/yande.re%201117669%20sample%20gochuumon_wa_usagi_desu_ka%3F%20hoto_cocoa%20koi%20seifuku%20ujimatsu_chiya.jpg",
        "sample_width": 1500,
        "score": 12,
        "source": "https://twitter.com/Kirara_Umeda221/status/1698120287047561685",
        "status": "active",
        "tags": "gochuumon_wa_usagi_desu_ka? hoto_cocoa koi seifuku ujimatsu_chiya",
        "updated_at": 1693716044,
        "width": 2024
    },
    {
        "actual_preview_height": 300,
        "actual_preview_width": 211,
        "approver_id": null,
        "author": "whitespace1",
        "change": 5622327,
        "created_at": 1691282313,
        "creator_id": 457203,
        "file_ext": "jpg",
        "file_size": 3226738,
        "file_url": "https://files.yande.re/image/9a10fea43c5244ba0bd226e95c6fe6e9/yande.re%201110698%20bikini%20gochuumon_wa_usagi_desu_ka%3F%20kafuu_chino%20kouda_suzu%20loli%20see_through%20shirt_lift%20swimsuits%20thong%20wet%20wet_clothes.jpg",
        "frames": [],
        "frames_pending": [],
        "frames_pending_string": "",
        "frames_string": "",
        "has_children": false,
        "height": 2670,
        "id": 1110698,
        "is_held": false,
        "is_note_locked": false,
        "is_pending": false,
        "is_rating_locked": false,
        "is_shown_in_index": true,
        "jpeg_file_size": 0,
        "jpeg_height": 2670,
        "jpeg_url": "https://files.yande.re/image/9a10fea43c5244ba0bd226e95c6fe6e9/yande.re%201110698%20bikini%20gochuumon_wa_usagi_desu_ka%3F%20kafuu_chino%20kouda_suzu%20loli%20see_through%20shirt_lift%20swimsuits%20thong%20wet%20wet_clothes.jpg",
        "jpeg_width": 1882,
        "last_commented_at": 0,
        "last_noted_at": 0,
        "md5": "9a10fea43c5244ba0bd226e95c6fe6e9",
        "parent_id": null,
        "preview_height": 150,
        "preview_url": "https://assets.yande.re/data/preview/9a/10/9a10fea43c5244ba0bd226e95c6fe6e9.jpg",
        "preview_width": 106,
        "rating": "q",
        "sample_file_size": 289159,
        "sample_height": 1500,
        "sample_url": "https://files.yande.re/sample/9a10fea43c5244ba0bd226e95c6fe6e9/yande.re%201110698%20sample%20bikini%20gochuumon_wa_usagi_desu_ka%3F%20kafuu_chino%20kouda_suzu%20loli%20see_through%20shirt_lift%20swimsuits%20thong%20wet%20wet_clothes.jpg",
        "sample_width": 1057,
        "score": 56,
        "source": "https://i.pximg.net/img-original/img/2023/08/06/00/12/55/110562758_p0.jpg",
        "status": "active",
        "tags": "bikini gochuumon_wa_usagi_desu_ka? kafuu_chino kouda_suzu loli see_through shirt_lift swimsuits thong wet wet_clothes",
        "updated_at": 1691283057,
        "width": 1882
    },
    {
        "actual_preview_height": 212,
        "actual_preview_width": 300,
        "approver_id": null,
        "author": "whitespace1",
        "change": 5613144,
        "created_at": 1690607161,
        "creator_id": 457203,
        "file_ext": "jpg",
        "file_size": 7049360,
        "file_url": "https://files.yande.re/image/6a0fe3600a6ddb6fb7ae6b087719be65/yande.re%201108781%20ass%20chinomaron%20gochuumon_wa_usagi_desu_ka%3F%20kafuu_chino%20loli%20seifuku%20skirt_lift.jpg",
        "frames": [],
        "frames_pending": [],
        "frames_pending_string": "",
        "frames_string": "",
        "has_children": false,
        "height": 3182,
        "id": 1108781,
        "is_held": false,
        "is_note_locked": false,
        "is_pending": false,
        "is_rating_locked": false,
        "is_shown_in_index": true,
        "jpeg_file_size": 0,
        "jpeg_height": 3182,
        "jpeg_url": "https://files.yande.re/image/6a0fe3600a6ddb6fb7ae6b087719be65/yande.re%201108781%20ass%20chinomaron%20gochuumon_wa_usagi_desu_ka%3F%20kafuu_chino%20loli%20seifuku%20skirt_lift.jpg",
        "jpeg_width": 4500,
        "last_commented_at": 0,
        "last_noted_at": 0,
        "md5": "6a0fe3600a6ddb6fb7ae6b087719be65",
        "parent_id": null,
        "preview_height": 106,
        "preview_url": "https://assets.yande.re/data/preview/6a/0f/6a0fe3600a6ddb6fb7ae6b087719be65.jpg",
        "preview_width": 150,
        "rating": "q",
        "sample_file_size": 327872,
        "sample_height": 1061,
        "sample_url": "https://files.yande.re/sample/6a0fe3600a6ddb6fb7ae6b087719be65/yande.re%201108781%20sample%20ass%20chinomaron%20gochuumon_wa_usagi_desu_ka%3F%20kafuu_chino%20loli%20seifuku%20skirt_lift.jpg",
        "sample_width": 1500,
        "score": 28,
        "source": "",
        "status": "active",
        "tags": "ass chinomaron gochuumon_wa_usagi_desu_ka? kafuu_chino loli seifuku skirt_lift",
        "updated_at": 1690607191,
        "width": 4500
    },
    {
        "actual_preview_height": 300,
        "actual_preview_width": 214,
        "approver_id": null,
        "author": "whitespace1",
        "change": 5605213,
        "created_at": 1689830901,
        "creator_id": 457203,
        "file_ext": "jpg",
        "file_size": 535155,
        "file_url": "https://files.yande.re/image/5161aefadaf60081f4e18cb8178fc12c/yande.re%201106423%20bikini%20gochuumon_wa_usagi_desu_ka%3F%20kafuu_chino%20loli%20nipples%20rika-tan%20swimsuits%20topless.jpg",
        "frames": [],
        "frames_pending": [],
        "frames_pending_string": "",
        "frames_string": "",
        "has_children": false,
        "height": 2806,
        "id": 1106423,
        "is_held": false,
        "is_note_locked": false,
        "is_pending": false,
        "is_rating_locked": false,
        "is_shown_in_index": false,
        "jpeg_file_size": 0,
        "jpeg_height": 2806,
        "jpeg_url": "https://files.yande.re/image/5161aefadaf60081f4e18cb8178fc12c/yande.re%201106423%20bikini%20gochuumon_wa_usagi_desu_ka%3F%20kafuu_chino%20loli%20nipples%20rika-tan%20swimsuits%20topless.jpg",
        "jpeg_width": 2000,
        "last_commented_at": 0,
        "last_noted_at": 0,
        "md5": "5161aefadaf60081f4e18cb8178fc12c",
        "parent_id": 1106422,
        "preview_height": 150,
        "preview_url": "https://assets.yande.re/data/preview/51/61/5161aefadaf60081f4e18cb8178fc12c.jpg",
        "preview_width": 107,
        "rating": "q",
        "sample_file_size": 320474,
        "sample_height": 1500,
        "sample_url": "https://files.yande.re/sample/5161aefadaf60081f4e18cb8178fc12c/yande.re%201106423%20sample%20bikini%20gochuumon_wa_usagi_desu_ka%3F%20kafuu_chino%20loli%20nipples%20rika-tan%20swimsuits%20topless.jpg",
        "sample_width": 1069,
        "score": 84,
        "source": "https://fantia.jp/posts/2113998",
        "status": "active",
        "tags": "bikini gochuumon_wa_usagi_desu_ka? kafuu_chino loli nipples rika-tan swimsuits topless",
        "updated_at": 1690100396,
        "width": 2000
    },
    {
        "actual_preview_height": 300,
        "actual_preview_width": 214,
        "approver_id": null,
        "author": "whitespace1",
        "change": 5652437,
        "created_at": 1689830879,
        "creator_id": 457203,
        "file_ext": "jpg",
        "file_size": 564898,
        "file_url": "https://files.yande.re/image/acf7756a5123292e846cc7dac33599b9/yande.re%201106422%20bikini%20gochuumon_wa_usagi_desu_ka%3F%20kafuu_chino%20loli%20rika-tan%20swimsuits.jpg",
        "frames": [],
        "frames_pending": [],
        "frames_pending_string": "",
        "frames_string": "",
        "has_children": true,
        "height": 2806,
        "id": 1106422,
        "is_held": false,
        "is_note_locked": false,
        "is_pending": false,
        "is_rating_locked": false,
        "is_shown_in_index": true,
        "jpeg_file_size": 0,
        "jpeg_height": 2806,
        "jpeg_url": "https://files.yande.re/image/acf7756a5123292e846cc7dac33599b9/yande.re%201106422%20bikini%20gochuumon_wa_usagi_desu_ka%3F%20kafuu_chino%20loli%20rika-tan%20swimsuits.jpg",
        "jpeg_width": 2000,
        "last_commented_at": 0,
        "last_noted_at": 0,
        "md5": "acf7756a5123292e846cc7dac33599b9",
        "parent_id": null,
        "preview_height": 150,
        "preview_url": "https://assets.yande.re/data/preview/ac/f7/acf7756a5123292e846cc7dac33599b9.jpg",
        "preview_width": 107,
        "rating": "q",
        "sample_file_size": 335439,
        "sample_height": 1500,
        "sample_url": "https://files.yande.re/sample/acf7756a5123292e846cc7dac33599b9/yande.re%201106422%20sample%20bikini%20gochuumon_wa_usagi_desu_ka%3F%20kafuu_chino%20loli%20rika-tan%20swimsuits.jpg",
        "sample_width": 1069,
        "score": 60,
        "source": "https://fantia.jp/posts/2113998",
        "status": "active",
        "tags": "bikini gochuumon_wa_usagi_desu_ka? kafuu_chino loli rika-tan swimsuits",
        "updated_at": 1690100501,
        "width": 2000
    },
    {
        "actual_preview_height": 300,
        "actual_preview_width": 215,
        "approver_id": null,
        "author": "whitespace1",
        "change": 5605227,
        "created_at": 1689412378,
        "creator_id": 457203,
        "file_ext": "jpg",
        "file_size": 529479,
        "file_url": "https://files.yande.re/image/810083b6979aad97d6ec737a339489cb/yande.re%201105362%20cameltoe%20gochuumon_wa_usagi_desu_ka%3F%20kafuu_chino%20loli%20maid%20nipples%20pantsu%20rika-tan%20thong%20topless.jpg",
        "frames": [],
        "frames_pending": [],
        "frames_pending_string": "",
        "frames_string": "",
        "has_children": true,
        "height": 2791,
        "id": 1105362,
        "is_held": false,
        "is_note_locked": false,
        "is_pending": false,
        "is_rating_locked": false,
        "is_shown_in_index": true,
        "jpeg_file_size": 0,
        "jpeg_height": 2791,
        "jpeg_url": "https://files.yande.re/image/810083b6979aad97d6ec737a339489cb/yande.re%201105362%20cameltoe%20gochuumon_wa_usagi_desu_ka%3F%20kafuu_chino%20loli%20maid%20nipples%20pantsu%20rika-tan%20thong%20topless.jpg",
        "jpeg_width": 2000,
        "last_commented_at": 0,
        "last_noted_at": 0,
        "md5": "810083b6979aad97d6ec737a339489cb",
        "parent_id": null,
        "preview_height": 150,
        "preview_url": "https://assets.yande.re/data/preview/81/00/810083b6979aad97d6ec737a339489cb.jpg",
        "preview_width": 107,
        "rating": "q",
        "sample_file_size": 280738,
        "sample_height": 1500,
        "sample_url": "https://files.yande.re/sample/810083b6979aad97d6ec737a339489cb/yande.re%201105362%20sample%20cameltoe%20gochuumon_wa_usagi_desu_ka%3F%20kafuu_chino%20loli%20maid%20nipples%20pantsu%20rika-tan%20thong%20topless.jpg",
        "sample_width": 1075,
        "score": 204,
        "source": "https://fantia.jp/posts/2097560",
        "status": "active",
        "tags": "cameltoe gochuumon_wa_usagi_desu_ka? kafuu_chino loli maid nipples pantsu rika-tan thong topless",
        "updated_at": 1690101571,
        "width": 2000
    },
    {
        "actual_preview_height": 300,
        "actual_preview_width": 212,
        "approver_id": null,
        "author": "whitespace1",
        "change": 5605223,
        "created_at": 1688788190,
        "creator_id": 457203,
        "file_ext": "jpg",
        "file_size": 668734,
        "file_url": "https://files.yande.re/image/5d8f14c006e7e9d50f90bac6266b21db/yande.re%201103403%20breasts%20cameltoe%20gochuumon_wa_usagi_desu_ka%3F%20kafuu_chino%20loli%20maid%20nipples%20no_bra%20open_shirt%20pantsu%20rika-tan%20skirt_lift%20string_panties.jpg",
        "frames": [],
        "frames_pending": [],
        "frames_pending_string": "",
        "frames_string": "",
        "has_children": true,
        "height": 2825,
        "id": 1103403,
        "is_held": false,
        "is_note_locked": false,
        "is_pending": false,
        "is_rating_locked": false,
        "is_shown_in_index": true,
        "jpeg_file_size": 0,
        "jpeg_height": 2825,
        "jpeg_url": "https://files.yande.re/image/5d8f14c006e7e9d50f90bac6266b21db/yande.re%201103403%20breasts%20cameltoe%20gochuumon_wa_usagi_desu_ka%3F%20kafuu_chino%20loli%20maid%20nipples%20no_bra%20open_shirt%20pantsu%20rika-tan%20skirt_lift%20string_panties.jpg",
        "jpeg_width": 2000,
        "last_commented_at": 1688795135,
        "last_noted_at": 0,
        "md5": "5d8f14c006e7e9d50f90bac6266b21db",
        "parent_id": null,
        "preview_height": 150,
        "preview_url": "https://assets.yande.re/data/preview/5d/8f/5d8f14c006e7e9d50f90bac6266b21db.jpg",
        "preview_width": 106,
        "rating": "q",
        "sample_file_size": 350625,
        "sample_height": 1500,
        "sample_url": "https://files.yande.re/sample/5d8f14c006e7e9d50f90bac6266b21db/yande.re%201103403%20sample%20breasts%20cameltoe%20gochuumon_wa_usagi_desu_ka%3F%20kafuu_chino%20loli%20maid%20nipples%20no_bra%20open_shirt%20pantsu%20rika-tan%20skirt_lift%20string_panties.jpg",
        "sample_width": 1062,
        "score": 145,
        "source": "https://fantia.jp/posts/2089876",
        "status": "active",
        "tags": "breasts cameltoe gochuumon_wa_usagi_desu_ka? kafuu_chino loli maid nipples no_bra open_shirt pantsu rika-tan skirt_lift string_panties",
        "updated_at": 1690101302,
        "width": 2000
    },
    {
        "actual_preview_height": 300,
        "actual_preview_width": 212,
        "approver_id": null,
        "author": "BattlequeenYume",
        "change": 5575063,
        "created_at": 1687887285,
        "creator_id": 323282,
        "file_ext": "jpg",
        "file_size": 2075020,
        "file_url": "https://files.yande.re/image/83fc98416b16b66cb765dc976fca5bc5/yande.re%201100650%20bikini%20cameltoe%20erect_nipples%20fengshen_chino%20gochuumon_wa_usagi_desu_ka%3F%20kafuu_chino%20loli%20swimsuits%20thighhighs%20thong.jpg",
        "frames": [],
        "frames_pending": [],
        "frames_pending_string": "",
        "frames_string": "",
        "has_children": true,
        "height": 5100,
        "id": 1100650,
        "is_held": false,
        "is_note_locked": false,
        "is_pending": false,
        "is_rating_locked": false,
        "is_shown_in_index": true,
        "jpeg_file_size": 0,
        "jpeg_height": 5100,
        "jpeg_url": "https://files.yande.re/image/83fc98416b16b66cb765dc976fca5bc5/yande.re%201100650%20bikini%20cameltoe%20erect_nipples%20fengshen_chino%20gochuumon_wa_usagi_desu_ka%3F%20kafuu_chino%20loli%20swimsuits%20thighhighs%20thong.jpg",
        "jpeg_width": 3600,
        "last_commented_at": 0,
        "last_noted_at": 0,
        "md5": "83fc98416b16b66cb765dc976fca5bc5",
        "parent_id": null,
        "preview_height": 150,
        "preview_url": "https://assets.yande.re/data/preview/83/fc/83fc98416b16b66cb765dc976fca5bc5.jpg",
        "preview_width": 106,
        "rating": "q",
        "sample_file_size": 283623,
        "sample_height": 1500,
        "sample_url": "https://files.yande.re/sample/83fc98416b16b66cb765dc976fca5bc5/yande.re%201100650%20sample%20bikini%20cameltoe%20erect_nipples%20fengshen_chino%20gochuumon_wa_usagi_desu_ka%3F%20kafuu_chino%20loli%20swimsuits%20thighhighs%20thong.jpg",
        "sample_width": 1059,
        "score": 41,
        "source": "",
        "status": "active",
        "tags": "bikini cameltoe erect_nipples fengshen_chino gochuumon_wa_usagi_desu_ka? kafuu_chino loli swimsuits thighhighs thong",
        "updated_at": 1689365427,
        "width": 3600
    },
    {
        "actual_preview_height": 300,
        "actual_preview_width": 212,
        "approver_id": null,
        "author": "BattlequeenYume",
        "change": 5594447,
        "created_at": 1687702676,
        "creator_id": 323282,
        "file_ext": "jpg",
        "file_size": 1938357,
        "file_url": "https://files.yande.re/image/0811bb9c4e0c6dcae84f14c04ff0e5f7/yande.re%201099841%20breasts%20fengshen_chino%20gochuumon_wa_usagi_desu_ka%3F%20kafuu_chino%20loli%20nipples%20no_bra%20nopan%20open_shirt%20seifuku%20skirt_lift.jpg",
        "frames": [],
        "frames_pending": [],
        "frames_pending_string": "",
        "frames_string": "",
        "has_children": false,
        "height": 5100,
        "id": 1099841,
        "is_held": false,
        "is_note_locked": false,
        "is_pending": false,
        "is_rating_locked": false,
        "is_shown_in_index": true,
        "jpeg_file_size": 0,
        "jpeg_height": 5100,
        "jpeg_url": "https://files.yande.re/image/0811bb9c4e0c6dcae84f14c04ff0e5f7/yande.re%201099841%20breasts%20fengshen_chino%20gochuumon_wa_usagi_desu_ka%3F%20kafuu_chino%20loli%20nipples%20no_bra%20nopan%20open_shirt%20seifuku%20skirt_lift.jpg",
        "jpeg_width": 3600,
        "last_commented_at": 1689525865,
        "last_noted_at": 0,
        "md5": "0811bb9c4e0c6dcae84f14c04ff0e5f7",
        "parent_id": 1099840,
        "preview_height": 150,
        "preview_url": "https://assets.yande.re/data/preview/08/11/0811bb9c4e0c6dcae84f14c04ff0e5f7.jpg",
        "preview_width": 106,
        "rating": "q",
        "sample_file_size": 273926,
        "sample_height": 1500,
        "sample_url": "https://files.yande.re/sample/0811bb9c4e0c6dcae84f14c04ff0e5f7/yande.re%201099841%20sample%20breasts%20fengshen_chino%20gochuumon_wa_usagi_desu_ka%3F%20kafuu_chino%20loli%20nipples%20no_bra%20nopan%20open_shirt%20seifuku%20skirt_lift.jpg",
        "sample_width": 1059,
        "score": 47,
        "source": "",
        "status": "active",
        "tags": "breasts fengshen_chino gochuumon_wa_usagi_desu_ka? kafuu_chino loli nipples no_bra nopan open_shirt seifuku skirt_lift",
        "updated_at": 1689110345,
        "width": 3600
    },
    {
        "actual_preview_height": 300,
        "actual_preview_width": 212,
        "approver_id": null,
        "author": "BattlequeenYume",
        "change": 5571794,
        "created_at": 1687702616,
        "creator_id": 323282,
        "file_ext": "jpg",
        "file_size": 2003543,
        "file_url": "https://files.yande.re/image/fabcf75db2e373d7999e95036a55464b/yande.re%201099840%20bikini%20fengshen_chino%20gochuumon_wa_usagi_desu_ka%3F%20kafuu_chino%20loli%20open_shirt%20seifuku%20skirt_lift%20swimsuits.jpg",
        "frames": [],
        "frames_pending": [],
        "frames_pending_string": "",
        "frames_string": "",
        "has_children": true,
        "height": 5100,
        "id": 1099840,
        "is_held": false,
        "is_note_locked": false,
        "is_pending": false,
        "is_rating_locked": false,
        "is_shown_in_index": true,
        "jpeg_file_size": 0,
        "jpeg_height": 5100,
        "jpeg_url": "https://files.yande.re/image/fabcf75db2e373d7999e95036a55464b/yande.re%201099840%20bikini%20fengshen_chino%20gochuumon_wa_usagi_desu_ka%3F%20kafuu_chino%20loli%20open_shirt%20seifuku%20skirt_lift%20swimsuits.jpg",
        "jpeg_width": 3600,
        "last_commented_at": 0,
        "last_noted_at": 0,
        "md5": "fabcf75db2e373d7999e95036a55464b",
        "parent_id": null,
        "preview_height": 150,
        "preview_url": "https://assets.yande.re/data/preview/fa/bc/fabcf75db2e373d7999e95036a55464b.jpg",
        "preview_width": 106,
        "rating": "q",
        "sample_file_size": 281160,
        "sample_height": 1500,
        "sample_url": "https://files.yande.re/sample/fabcf75db2e373d7999e95036a55464b/yande.re%201099840%20sample%20bikini%20fengshen_chino%20gochuumon_wa_usagi_desu_ka%3F%20kafuu_chino%20loli%20open_shirt%20seifuku%20skirt_lift%20swimsuits.jpg",
        "sample_width": 1059,
        "score": 45,
        "source": "",
        "status": "active",
        "tags": "bikini fengshen_chino gochuumon_wa_usagi_desu_ka? kafuu_chino loli open_shirt seifuku skirt_lift swimsuits",
        "updated_at": 1688901739,
        "width": 3600
    },
    {
        "actual_preview_height": 212,
        "actual_preview_width": 300,
        "approver_id": null,
        "author": "BattlequeenYume",
        "change": 5571666,
        "created_at": 1687702143,
        "creator_id": 323282,
        "file_ext": "jpg",
        "file_size": 1877535,
        "file_url": "https://files.yande.re/image/b6fae32ace6fb169d9b6e1bca602c6a0/yande.re%201099833%20ass%20bra%20cameltoe%20fengshen_chino%20gochuumon_wa_usagi_desu_ka%3F%20kafuu_chino%20loli%20pantsu%20seifuku%20skirt_lift%20thong.jpg",
        "frames": [],
        "frames_pending": [],
        "frames_pending_string": "",
        "frames_string": "",
        "has_children": false,
        "height": 3600,
        "id": 1099833,
        "is_held": false,
        "is_note_locked": false,
        "is_pending": false,
        "is_rating_locked": false,
        "is_shown_in_index": true,
        "jpeg_file_size": 0,
        "jpeg_height": 3600,
        "jpeg_url": "https://files.yande.re/image/b6fae32ace6fb169d9b6e1bca602c6a0/yande.re%201099833%20ass%20bra%20cameltoe%20fengshen_chino%20gochuumon_wa_usagi_desu_ka%3F%20kafuu_chino%20loli%20pantsu%20seifuku%20skirt_lift%20thong.jpg",
        "jpeg_width": 5100,
        "last_commented_at": 0,
        "last_noted_at": 0,
        "md5": "b6fae32ace6fb169d9b6e1bca602c6a0",
        "parent_id": 1072654,
        "preview_height": 106,
        "preview_url": "https://assets.yande.re/data/preview/b6/fa/b6fae32ace6fb169d9b6e1bca602c6a0.jpg",
        "preview_width": 150,
        "rating": "q",
        "sample_file_size": 250852,
        "sample_height": 1059,
        "sample_url": "https://files.yande.re/sample/b6fae32ace6fb169d9b6e1bca602c6a0/yande.re%201099833%20sample%20ass%20bra%20cameltoe%20fengshen_chino%20gochuumon_wa_usagi_desu_ka%3F%20kafuu_chino%20loli%20pantsu%20seifuku%20skirt_lift%20thong.jpg",
        "sample_width": 1500,
        "score": 43,
        "source": "",
        "status": "active",
        "tags": "ass bra cameltoe fengshen_chino gochuumon_wa_usagi_desu_ka? kafuu_chino loli pantsu seifuku skirt_lift thong",
        "updated_at": 1689010248,
        "width": 5100
    },
    {
        "actual_preview_height": 300,
        "actual_preview_width": 94,
        "approver_id": null,
        "author": "BattlequeenYume",
        "change": 5571420,
        "created_at": 1687700658,
        "creator_id": 323282,
        "file_ext": "jpg",
        "file_size": 3820152,
        "file_url": "https://files.yande.re/image/cd98a95c98c4201e04765e3e782c38a3/yande.re%201099817%20cameltoe%20dakimakura%20fengshen_chino%20gochuumon_wa_usagi_desu_ka%3F%20kafuu_chino%20loli%20pantsu%20pasties%20thong%20topless.jpg",
        "frames": [],
        "frames_pending": [],
        "frames_pending_string": "",
        "frames_string": "",
        "has_children": true,
        "height": 9449,
        "id": 1099817,
        "is_held": false,
        "is_note_locked": false,
        "is_pending": false,
        "is_rating_locked": false,
        "is_shown_in_index": true,
        "jpeg_file_size": 0,
        "jpeg_height": 9449,
        "jpeg_url": "https://files.yande.re/image/cd98a95c98c4201e04765e3e782c38a3/yande.re%201099817%20cameltoe%20dakimakura%20fengshen_chino%20gochuumon_wa_usagi_desu_ka%3F%20kafuu_chino%20loli%20pantsu%20pasties%20thong%20topless.jpg",
        "jpeg_width": 2953,
        "last_commented_at": 0,
        "last_noted_at": 0,
        "md5": "cd98a95c98c4201e04765e3e782c38a3",
        "parent_id": null,
        "preview_height": 150,
        "preview_url": "https://assets.yande.re/data/preview/cd/98/cd98a95c98c4201e04765e3e782c38a3.jpg",
        "preview_width": 47,
        "rating": "q",
        "sample_file_size": 145596,
        "sample_height": 1500,
        "sample_url": "https://files.yande.re/sample/cd98a95c98c4201e04765e3e782c38a3/yande.re%201099817%20sample%20cameltoe%20dakimakura%20fengshen_chino%20gochuumon_wa_usagi_desu_ka%3F%20kafuu_chino%20loli%20pantsu%20pasties%20thong%20topless.jpg",
        "sample_width": 469,
        "score": 39,
        "source": "",
        "status": "active",
        "tags": "cameltoe dakimakura fengshen_chino gochuumon_wa_usagi_desu_ka? kafuu_chino loli pantsu pasties thong topless",
        "updated_at": 1688901736,
        "width": 2953
    },
    {
        "actual_preview_height": 300,
        "actual_preview_width": 212,
        "approver_id": null,
        "author": "Yuki937",
        "change": 5535250,
        "created_at": 1684909756,
        "creator_id": 539417,
        "file_ext": "jpg",
        "file_size": 9947965,
        "file_url": "https://files.yande.re/image/8aafc096c072d4ef4d4c2a45ba824397/yande.re%201091705%20chinomaron%20gochuumon_wa_usagi_desu_ka%3F%20kafuu_chino%20loli%20pantsu%20thighhighs.jpg",
        "frames": [],
        "frames_pending": [],
        "frames_pending_string": "",
        "frames_string": "",
        "has_children": false,
        "height": 4093,
        "id": 1091705,
        "is_held": false,
        "is_note_locked": false,
        "is_pending": false,
        "is_rating_locked": false,
        "is_shown_in_index": true,
        "jpeg_file_size": 0,
        "jpeg_height": 4093,
        "jpeg_url": "https://files.yande.re/image/8aafc096c072d4ef4d4c2a45ba824397/yande.re%201091705%20chinomaron%20gochuumon_wa_usagi_desu_ka%3F%20kafuu_chino%20loli%20pantsu%20thighhighs.jpg",
        "jpeg_width": 2894,
        "last_commented_at": 0,
        "last_noted_at": 0,
        "md5": "8aafc096c072d4ef4d4c2a45ba824397",
        "parent_id": null,
        "preview_height": 150,
        "preview_url": "https://assets.yande.re/data/preview/8a/af/8aafc096c072d4ef4d4c2a45ba824397.jpg",
        "preview_width": 106,
        "rating": "q",
        "sample_file_size": 321692,
        "sample_height": 1500,
        "sample_url": "https://files.yande.re/sample/8aafc096c072d4ef4d4c2a45ba824397/yande.re%201091705%20sample%20chinomaron%20gochuumon_wa_usagi_desu_ka%3F%20kafuu_chino%20loli%20pantsu%20thighhighs.jpg",
        "sample_width": 1061,
        "score": 30,
        "source": "",
        "status": "active",
        "tags": "chinomaron gochuumon_wa_usagi_desu_ka? kafuu_chino loli pantsu thighhighs",
        "updated_at": 1684909756,
        "width": 2894
    },
    {
        "actual_preview_height": 300,
        "actual_preview_width": 212,
        "approver_id": null,
        "author": "Yuki937",
        "change": 5534477,
        "created_at": 1684909612,
        "creator_id": 539417,
        "file_ext": "png",
        "file_size": 5573975,
        "file_url": "https://files.yande.re/image/5c7cd647a0042a7454077cc07c202803/yande.re%201091701%20angel%20bottomless%20fuiba_fuyu%20gochuumon_wa_usagi_desu_ka%3F%20loli%20tsukimi_%28xiaohuasan%29%20wings.png",
        "frames": [],
        "frames_pending": [],
        "frames_pending_string": "",
        "frames_string": "",
        "has_children": false,
        "height": 4244,
        "id": 1091701,
        "is_held": false,
        "is_note_locked": false,
        "is_pending": false,
        "is_rating_locked": false,
        "is_shown_in_index": true,
        "jpeg_file_size": 1369633,
        "jpeg_height": 4244,
        "jpeg_url": "https://files.yande.re/jpeg/5c7cd647a0042a7454077cc07c202803/yande.re%201091701%20angel%20bottomless%20fuiba_fuyu%20gochuumon_wa_usagi_desu_ka%3F%20loli%20tsukimi_%28xiaohuasan%29%20wings.jpg",
        "jpeg_width": 3000,
        "last_commented_at": 0,
        "last_noted_at": 0,
        "md5": "5c7cd647a0042a7454077cc07c202803",
        "parent_id": null,
        "preview_height": 150,
        "preview_url": "https://assets.yande.re/data/preview/5c/7c/5c7cd647a0042a7454077cc07c202803.jpg",
        "preview_width": 106,
        "rating": "q",
        "sample_file_size": 283391,
        "sample_height": 1500,
        "sample_url": "https://files.yande.re/sample/5c7cd647a0042a7454077cc07c202803/yande.re%201091701%20sample%20angel%20bottomless%20fuiba_fuyu%20gochuumon_wa_usagi_desu_ka%3F%20loli%20tsukimi_%28xiaohuasan%29%20wings.jpg",
        "sample_width": 1060,
        "score": 24,
        "source": "",
        "status": "active",
        "tags": "angel bottomless fuiba_fuyu gochuumon_wa_usagi_desu_ka? loli tsukimi_(xiaohuasan) wings",
        "updated_at": 1684909612,
        "width": 3000
    },
    {
        "actual_preview_height": 300,
        "actual_preview_width": 215,
        "approver_id": null,
        "author": "Yuki937",
        "change": 5534467,
        "created_at": 1684909539,
        "creator_id": 539417,
        "file_ext": "png",
        "file_size": 7697218,
        "file_url": "https://files.yande.re/image/2e7e33aea0b5cc9a5785740a204d872b/yande.re%201091699%20bikini%20gochuumon_wa_usagi_desu_ka%3F%20kafuu_chino%20loli%20pizzzica%20swimsuits.png",
        "frames": [],
        "frames_pending": [],
        "frames_pending_string": "",
        "frames_string": "",
        "has_children": true,
        "height": 4096,
        "id": 1091699,
        "is_held": false,
        "is_note_locked": false,
        "is_pending": false,
        "is_rating_locked": false,
        "is_shown_in_index": true,
        "jpeg_file_size": 1461469,
        "jpeg_height": 4096,
        "jpeg_url": "https://files.yande.re/jpeg/2e7e33aea0b5cc9a5785740a204d872b/yande.re%201091699%20bikini%20gochuumon_wa_usagi_desu_ka%3F%20kafuu_chino%20loli%20pizzzica%20swimsuits.jpg",
        "jpeg_width": 2935,
        "last_commented_at": 0,
        "last_noted_at": 0,
        "md5": "2e7e33aea0b5cc9a5785740a204d872b",
        "parent_id": null,
        "preview_height": 150,
        "preview_url": "https://assets.yande.re/data/preview/2e/7e/2e7e33aea0b5cc9a5785740a204d872b.jpg",
        "preview_width": 107,
        "rating": "q",
        "sample_file_size": 281892,
        "sample_height": 1500,
        "sample_url": "https://files.yande.re/sample/2e7e33aea0b5cc9a5785740a204d872b/yande.re%201091699%20sample%20bikini%20gochuumon_wa_usagi_desu_ka%3F%20kafuu_chino%20loli%20pizzzica%20swimsuits.jpg",
        "sample_width": 1075,
        "score": 28,
        "source": "",
        "status": "active",
        "tags": "bikini gochuumon_wa_usagi_desu_ka? kafuu_chino loli pizzzica swimsuits",
        "updated_at": 1684909540,
        "width": 2935
    },
    {
        "actual_preview_height": 300,
        "actual_preview_width": 193,
        "approver_id": null,
        "author": "Yuki937",
        "change": 5535248,
        "created_at": 1684909468,
        "creator_id": 539417,
        "file_ext": "png",
        "file_size": 5717815,
        "file_url": "https://files.yande.re/image/be442a3c62b222204276e1e13e66f417/yande.re%201091698%20ass%20fuiba_fuyu%20gochuumon_wa_usagi_desu_ka%3F%20loli%20naked_apron%20pizzzica.png",
        "frames": [],
        "frames_pending": [],
        "frames_pending_string": "",
        "frames_string": "",
        "has_children": false,
        "height": 3783,
        "id": 1091698,
        "is_held": false,
        "is_note_locked": false,
        "is_pending": false,
        "is_rating_locked": false,
        "is_shown_in_index": true,
        "jpeg_file_size": 937534,
        "jpeg_height": 3783,
        "jpeg_url": "https://files.yande.re/jpeg/be442a3c62b222204276e1e13e66f417/yande.re%201091698%20ass%20fuiba_fuyu%20gochuumon_wa_usagi_desu_ka%3F%20loli%20naked_apron%20pizzzica.jpg",
        "jpeg_width": 2428,
        "last_commented_at": 0,
        "last_noted_at": 0,
        "md5": "be442a3c62b222204276e1e13e66f417",
        "parent_id": null,
        "preview_height": 150,
        "preview_url": "https://assets.yande.re/data/preview/be/44/be442a3c62b222204276e1e13e66f417.jpg",
        "preview_width": 96,
        "rating": "q",
        "sample_file_size": 195831,
        "sample_height": 1500,
        "sample_url": "https://files.yande.re/sample/be442a3c62b222204276e1e13e66f417/yande.re%201091698%20sample%20ass%20fuiba_fuyu%20gochuumon_wa_usagi_desu_ka%3F%20loli%20naked_apron%20pizzzica.jpg",
        "sample_width": 963,
        "score": 49,
        "source": "",
        "status": "active",
        "tags": "ass fuiba_fuyu gochuumon_wa_usagi_desu_ka? loli naked_apron pizzzica",
        "updated_at": 1684909468,
        "width": 2428
    },
    {
        "actual_preview_height": 300,
        "actual_preview_width": 231,
        "approver_id": null,
        "author": "Lzhom",
        "change": 5504806,
        "created_at": 1682770715,
        "creator_id": 513205,
        "file_ext": "jpg",
        "file_size": 15450979,
        "file_url": "https://files.yande.re/image/ec51f90838c84361158afb231fe1fee1/yande.re%201085076%20gochuumon_wa_usagi_desu_ka%3F%20loli%20natsu_megumi%20nipples%20sakamatashachi%20topless.jpg",
        "frames": [],
        "frames_pending": [],
        "frames_pending_string": "",
        "frames_string": "",
        "has_children": false,
        "height": 13000,
        "id": 1085076,
        "is_held": false,
        "is_note_locked": false,
        "is_pending": false,
        "is_rating_locked": false,
        "is_shown_in_index": true,
        "jpeg_file_size": 0,
        "jpeg_height": 13000,
        "jpeg_url": "https://files.yande.re/image/ec51f90838c84361158afb231fe1fee1/yande.re%201085076%20gochuumon_wa_usagi_desu_ka%3F%20loli%20natsu_megumi%20nipples%20sakamatashachi%20topless.jpg",
        "jpeg_width": 10000,
        "last_commented_at": 0,
        "last_noted_at": 0,
        "md5": "ec51f90838c84361158afb231fe1fee1",
        "parent_id": null,
        "preview_height": 150,
        "preview_url": "https://assets.yande.re/data/preview/ec/51/ec51f90838c84361158afb231fe1fee1.jpg",
        "preview_width": 115,
        "rating": "q",
        "sample_file_size": 225087,
        "sample_height": 1500,
        "sample_url": "https://files.yande.re/sample/ec51f90838c84361158afb231fe1fee1/yande.re%201085076%20sample%20gochuumon_wa_usagi_desu_ka%3F%20loli%20natsu_megumi%20nipples%20sakamatashachi%20topless.jpg",
        "sample_width": 1154,
        "score": 44,
        "source": "",
        "status": "active",
        "tags": "gochuumon_wa_usagi_desu_ka? loli natsu_megumi nipples sakamatashachi topless",
        "updated_at": 1682883159,
        "width": 10000
    }
]