[
    {
        "actual_preview_height": 300,
        "actual_preview_width": 212,
        "approver_id": null,
        "author": "TagMeMeMe!",
        "change": 5670002,
        "created_at": 1694812261,
        "creator_id": 485578,
        "file_ext": "jpg",
        "file_size": 629866,
        "file_url": "https://files.yande.re/image/eab5db9cbbb75c4b58dc34d4ce33aec7/yande.re%201120488%20airando%20animal_ears%20breasts%20bunny_ears%20bunny_girl%20fishnets%20kirigaya_suguha%20nipples%20no_bra%20pantyhose%20sword_art_online.jpg",
        "frames": [],
        "frames_pending": [],
        "frames_pending_string": "",
        "frames_string": "",
        "has_children": false,
        "height": 4094,
        "id": 1120488,
        "is_held": false,
        "is_note_locked": false,
        "is_pending": false,
        "is_rating_locked": false,
        "is_shown_in_index": true,
        "jpeg_file_size": 0,
        "jpeg_height": 4094,
        "jpeg_url": "https://files.yande.re/image/eab5db9cbbb75c4b58dc34d4ce33aec7/yande.re%201120488%20airando%20animal_ears%20breasts%20bunny_ears%20bunny_girl%20fishnets%20kirigaya_suguha%20nipples%20no_bra%20pantyhose%20sword_art_online.jpg",
        "jpeg_width": 2894,
        "last_commented_at": 0,
        "last_noted_at": 0,
        "md5": "eab5db9cbbb75c4b58dc34d4ce33aec7",
        "parent_id": 1120487,
        "preview_height": 150,
        "preview_url": "https://assets.yande.re/data/preview/ea/b5/eab5db9cbbb75c4b58dc34d4ce33aec7.jpg",
        "preview_width": 106,
        "rating": "q",
        "sample_file_size": 205922,
        "sample_height": 1500,
        "sample_url": "https://files.yande.re/sample/eab5db9cbbb75c4b58dc34d4ce33aec7/yande.re%201120488%20sample%20airando%20animal_ears%20breasts%20bunny_ears%20bunny_girl%20fishnets%20kirigaya_suguha%20nipples%20no_bra%20pantyhose%20sword_art_online.jpg",
        "sample_width": 1060,
        "score": 29,
        "source": "https://twitter.com/island_kossori/status/1198209569224183809",
        "status": "active",
        "tags": "airando animal_ears breasts bunny_ears bunny_girl fishnets kirigaya_suguha nipples no_bra pantyhose sword_art_online",
        "updated_at": 1694812261,
        "width": 2894
    },
    {
        "actual_preview_height": 300,
        "actual_preview_width": 212,
        "approver_id": null,
        "author": "TagMeMeMe!",
        "change": 5670000,
        "created_at": 1694812250,
        "creator_id": 485578,
        "file_ext": "jpg",
        "file_size": 2788191,
        "file_url": "https://files.yande.re/image/8f6d6824a5700c55e6b37d6d723dc4f1/yande.re%201120487%20airando%20animal_ears%20bunny_ears%20bunny_girl%20fishnets%20kirigaya_suguha%20no_bra%20pantyhose%20sword_art_online.jpg",
        "frames": [],
        "frames_pending": [],
        "frames_pending_string": "",
        "frames_string": "",
        "has_children": true,
        "height": 4094,
        "id": 1120487,
        "is_held": false,
        "is_note_locked": false,
        "is_pending": false,
        "is_rating_locked": false,
        "is_shown_in_index": true,
        "jpeg_file_size": 0,
        "jpeg_height": 4094,
        "jpeg_url": "https://files.yande.re/image/8f6d6824a5700c55e6b37d6d723dc4f1/yande.re%201120487%20airando%20animal_ears%20bunny_ears%20bunny_girl%20fishnets%20kirigaya_suguha%20no_bra%20pantyhose%20sword_art_online.jpg",
        "jpeg_width": 2894,
        "last_commented_at": 0,
        "last_noted_at": 0,
        "md5": "8f6d6824a5700c55e6b37d6d723dc4f1",
        "parent_id": null,
        "preview_height": 150,
        "preview_url": "https://assets.yande.re/data/preview/8f/6d/8f6d6824a5700c55e6b37d6d723dc4f1.jpg",
        "preview_width": 106,
        "rating": "q",
        "sample_file_size": 235988,
        "sample_height": 1500,
        "sample_url": "https://files.yande.re/sample/8f6d6824a5700c55e6b37d6d723dc4f1/yande.re%201120487%20sample%20airando%20animal_ears%20bunny_ears%20bunny_girl%20fishnets%20kirigaya_suguha%20no_bra%20pantyhose%20sword_art_online.jpg",
        "sample_width": 1060,
        "score": 19,
        "source": "https://twitter.com/island_kossori/status/1223599986576773122",
        "status": "active",
        "tags": "airando animal_ears bunny_ears bunny_girl fishnets kirigaya_suguha no_bra pantyhose sword_art_online",
        "updated_at": 1694812250,
        "width": 2894
    },
    {
        "actual_preview_height": 300,
        "actual_preview_width": 212,
        "approver_id": null,
        "author": "TagMeMeMe!",
        "change": 5670656,
        "created_at": 1694811115,
        "creator_id": 485578,
        "file_ext": "jpg",
        "file_size": 641789,
        "file_url": "https://files.yande.re/image/deb759c987ea6f78040e02c6973d52f8/yande.re%201120486%20airando%20lisbeth%20shinozaki_rika%20sword_art_online%20topless.jpg",
        "frames": [],
        "frames_pending": [],
        "frames_pending_string": "",
        "frames_string": "",
        "has_children": false,
        "height": 4096,
        "id": 1120486,
        "is_held": false,
        "is_note_locked": false,
        "is_pending": false,
        "is_rating_locked": false,
        "is_shown_in_index": true,
        "jpeg_file_size": 0,
        "jpeg_height": 4096,
        "jpeg_url": "https://files.yande.re/image/deb759c987ea6f78040e02c6973d52f8/yande.re%201120486%20airando%20lisbeth%20shinozaki_rika%20sword_art_online%20topless.jpg",
        "jpeg_width": 2896,
        "last_commented_at": 0,
        "last_noted_at": 0,
        "md5": "deb759c987ea6f78040e02c6973d52f8",
        "parent_id": null,
        "preview_height": 150,
        "preview_url": "https://assets.yande.re/data/preview/de/b7/deb759c987ea6f78040e02c6973d52f8.jpg",
        "preview_width": 106,
        "rating": "q",
        "sample_file_size": 224833,
        "sample_height": 1500,
        "sample_url": "https://files.yande.re/sample/deb759c987ea6f78040e02c6973d52f8/yande.re%201120486%20sample%20airando%20lisbeth%20shinozaki_rika%20sword_art_online%20topless.jpg",
        "sample_width": 1061,
        "score": 24,
        "source": "https://twitter.com/island_kossori/status/1530764004930441217",
        "status": "active",
        "tags": "airando lisbeth shinozaki_rika sword_art_online topless",
        "updated_at": 1694811115,
        "width": 2896
    },
    {
        "actual_preview_height": 300,
        "actual_preview_width": 212,
        "approver_id": null,
        "author": "TagMeMeMe!",
        "change": 5670655,
        "created_at": 1694811107,
        "creator_id": 485578,
        "file_ext": "jpg",
        "file_size": 1006995,
        "file_url": "https://files.yande.re/image/3df52347eef84b12f08ca1a66fdf2556/yande.re%201120485%20airando%20animal_ears%20breast_hold%20bunny_ears%20bunny_girl%20fishnets%20lisbeth%20no_bra%20pantyhose%20shinozaki_rika%20sword_art_online.jpg",
        "frames": [],
        "frames_pending": [],
        "frames_pending_string": "",
        "frames_string": "",
        "has_children": true,
        "height": 4096,
        "id": 1120485,
        "is_held": false,
        "is_note_locked": false,
        "is_pending": false,
        "is_rating_locked": false,
        "is_shown_in_index": true,
        "jpeg_file_size": 0,
        "jpeg_height": 4096,
        "jpeg_url": "https://files.yande.re/image/3df52347eef84b12f08ca1a66fdf2556/yande.re%201120485%20airando%20animal_ears%20breast_hold%20bunny_ears%20bunny_girl%20fishnets%20lisbeth%20no_bra%20pantyhose%20shinozaki_rika%20sword_art_online.jpg",
        "jpeg_width": 2896,
        "last_commented_at": 0,
        "last_noted_at": 0,
        "md5": "3df52347eef84b12f08ca1a66fdf2556",
        "parent_id": null,
        "preview_height": 150,
        "preview_url": "https://assets.yande.re/data/preview/3d/f5/3df52347eef84b12f08ca1a66fdf2556.jpg",
        "preview_width": 106,
        "rating": "q",
        "sample_file_size": 317937,
        "sample_height": 1500,
        "sample_url": "https://files.yande.re/sample/3df52347eef84b12f08ca1a66fdf2556/yande.re%201120485%20sample%20airando%20animal_ears%20breast_hold%20bunny_ears%20bunny_girl%20fishnets%20lisbeth%20no_bra%20pantyhose%20shinozaki_rika%20sword_art_online.jpg",
        "sample_width": 1061,
        "score": 18,
        "source": "https://twitter.com/island_kossori/status/1530764004930441217",
        "status": "active",
        "tags": "airando animal_ears breast_hold bunny_ears bunny_girl fishnets lisbeth no_bra pantyhose shinozaki_rika sword_art_online",
        "updated_at": 1694811109,
        "width": 2896
    },
    {
        "actual_preview_height": 300,
        "actual_preview_width": 212,
        "approver_id": null,
        "author": "TagMeMeMe!",
        "change": 5669956,
        "created_at": 1694810788,
        "creator_id": 485578,
        "file_ext": "jpg",
        "file_size": 8718887,
        "file_url": "https://files.yande.re/image/953af10084f6bbafe793bd4e341b3b61/yande.re%201120484%20airando%20alice_zuberg%20animal_ears%20bunny_ears%20bunny_girl%20fishnets%20no_bra%20pantyhose%20possible_duplicate%20sword_art_online%20sword_art_online_alicization.jpg",
        "frames": [],
        "frames_pending": [],
        "frames_pending_string": "",
        "frames_string": "",
        "has_children": true,
        "height": 5263,
        "id": 1120484,
        "is_held": false,
        "is_note_locked": false,
        "is_pending": false,
        "is_rating_locked": false,
        "is_shown_in_index": true,
        "jpeg_file_size": 0,
        "jpeg_height": 5263,
        "jpeg_url": "https://files.yande.re/image/953af10084f6bbafe793bd4e341b3b61/yande.re%201120484%20airando%20alice_zuberg%20animal_ears%20bunny_ears%20bunny_girl%20fishnets%20no_bra%20pantyhose%20possible_duplicate%20sword_art_online%20sword_art_online_alicization.jpg",
        "jpeg_width": 3721,
        "last_commented_at": 0,
        "last_noted_at": 0,
        "md5": "953af10084f6bbafe793bd4e341b3b61",
        "parent_id": null,
        "preview_height": 150,
        "preview_url": "https://assets.yande.re/data/preview/95/3a/953af10084f6bbafe793bd4e341b3b61.jpg",
        "preview_width": 106,
        "rating": "q",
        "sample_file_size": 379190,
        "sample_height": 1500,
        "sample_url": "https://files.yande.re/sample/953af10084f6bbafe793bd4e341b3b61/yande.re%201120484%20sample%20airando%20alice_zuberg%20animal_ears%20bunny_ears%20bunny_girl%20fishnets%20no_bra%20pantyhose%20possible_duplicate%20sword_art_online%20sword_art_online_alicization.jpg",
        "sample_width": 1061,
        "score": 18,
        "source": "https://i.pximg.net/img-original/img/2019/10/13/18/28/55/77268555_p0.jpg",
        "status": "active",
        "tags": "airando alice_zuberg animal_ears bunny_ears bunny_girl fishnets no_bra pantyhose possible_duplicate sword_art_online sword_art_online_alicization",
        "updated_at": 1694810789,
        "width": 3721
    },
    {
        "actual_preview_height": 300,
        "actual_preview_width": 212,
        "approver_id": null,
        "author": "TagMeMeMe!",
        "change": 5669962,
        "created_at": 1694810591,
        "creator_id": 485578,
        "file_ext": "jpg",
        "file_size": 7315524,
        "file_url": "https://files.yande.re/image/6607077b09debe2455c30c633c72fe48/yande.re%201120482%20airando%20animal_ears%20breasts%20bunny_ears%20bunny_girl%20fishnets%20konno_yuuki%20nipples%20no_bra%20pantyhose%20pointy_ears%20sword_art_online.jpg",
        "frames": [],
        "frames_pending": [],
        "frames_pending_string": "",
        "frames_string": "",
        "has_children": false,
        "height": 5263,
        "id": 1120482,
        "is_held": false,
        "is_note_locked": false,
        "is_pending": false,
        "is_rating_locked": false,
        "is_shown_in_index": true,
        "jpeg_file_size": 0,
        "jpeg_height": 5263,
        "jpeg_url": "https://files.yande.re/image/6607077b09debe2455c30c633c72fe48/yande.re%201120482%20airando%20animal_ears%20breasts%20bunny_ears%20bunny_girl%20fishnets%20konno_yuuki%20nipples%20no_bra%20pantyhose%20pointy_ears%20sword_art_online.jpg",
        "jpeg_width": 3721,
        "last_commented_at": 0,
        "last_noted_at": 0,
        "md5": "6607077b09debe2455c30c633c72fe48",
        "parent_id": null,
        "preview_height": 150,
        "preview_url": "https://assets.yande.re/data/preview/66/07/6607077b09debe2455c30c633c72fe48.jpg",
        "preview_width": 106,
        "rating": "q",
        "sample_file_size": 296812,
        "sample_height": 1500,
        "sample_url": "https://files.yande.re/sample/6607077b09debe2455c30c633c72fe48/yande.re%201120482%20sample%20airando%20animal_ears%20breasts%20bunny_ears%20bunny_girl%20fishnets%20konno_yuuki%20nipples%20no_bra%20pantyhose%20pointy_ears%20sword_art_online.jpg",
        "sample_width": 1061,
        "score": 21,
        "source": "https://i.pximg.net/img-original/img/2019/11/03/19/02/21/77632495_p1.jpg",
        "status": "active",
        "tags": "airando animal_ears breasts bunny_ears bunny_girl fishnets konno_yuuki nipples no_bra pantyhose pointy_ears sword_art_online",
        "updated_at": 1694810591,
        "width": 3721
    },
    {
        "actual_preview_height": 300,
        "actual_preview_width": 212,
        "approver_id": null,
        "author": "TagMeMeMe!",
        "change": 5670163,
        "created_at": 1694810503,
        "creator_id": 485578,
        "file_ext": "jpg",
        "file_size": 4774425,
        "file_url": "https://files.yande.re/image/77304899a6f7f508e94c4311f1be45b8/yande.re%201120481%20airando%20animal_ears%20breasts%20bunny_ears%20bunny_girl%20fishnets%20leafa%20nipples%20no_bra%20pantyhose%20pointy_ears%20sword_art_online.jpg",
        "frames": [],
        "frames_pending": [],
        "frames_pending_string": "",
        "frames_string": "",
        "has_children": false,
        "height": 4094,
        "id": 1120481,
        "is_held": false,
        "is_note_locked": false,
        "is_pending": false,
        "is_rating_locked": false,
        "is_shown_in_index": true,
        "jpeg_file_size": 0,
        "jpeg_height": 4094,
        "jpeg_url": "https://files.yande.re/image/77304899a6f7f508e94c4311f1be45b8/yande.re%201120481%20airando%20animal_ears%20breasts%20bunny_ears%20bunny_girl%20fishnets%20leafa%20nipples%20no_bra%20pantyhose%20pointy_ears%20sword_art_online.jpg",
        "jpeg_width": 2894,
        "last_commented_at": 0,
        "last_noted_at": 0,
        "md5": "77304899a6f7f508e94c4311f1be45b8",
        "parent_id": null,
        "preview_height": 150,
        "preview_url": "https://assets.yande.re/data/preview/77/30/77304899a6f7f508e94c4311f1be45b8.jpg",
        "preview_width": 106,
        "rating": "q",
        "sample_file_size": 281318,
        "sample_height": 1500,
        "sample_url": "https://files.yande.re/sample/77304899a6f7f508e94c4311f1be45b8/yande.re%201120481%20sample%20airando%20animal_ears%20breasts%20bunny_ears%20bunny_girl%20fishnets%20leafa%20nipples%20no_bra%20pantyhose%20pointy_ears%20sword_art_online.jpg",
        "sample_width": 1060,
        "score": 22,
        "source": "https://i.pximg.net/img-original/img/2019/11/23/20/48/10/77955178_p1.jpg",
        "status": "active",
        "tags": "airando animal_ears breasts bunny_ears bunny_girl fishnets leafa nipples no_bra pantyhose pointy_ears sword_art_online",
        "updated_at": 1694810503,
        "width": 2894
    },
    {
        "actual_preview_height": 300,
        "actual_preview_width": 212,
        "approver_id": null,
        "author": "TagMeMeMe!",
        "change": 5670653,
        "created_at": 1694810361,
        "creator_id": 485578,
        "file_ext": "jpg",
        "file_size": 5494160,
        "file_url": "https://files.yande.re/image/75bc28b71241ba3e1efadbfe571c429e/yande.re%201120480%20airando%20animal_ears%20asada_shino%20breasts%20bunny_ears%20bunny_girl%20nipples%20no_bra%20sinon%20sword_art_online.jpg",
        "frames": [],
        "frames_pending": [],
        "frames_pending_string": "",
        "frames_string": "",
        "has_children": false,
        "height": 5263,
        "id": 1120480,
        "is_held": false,
        "is_note_locked": false,
        "is_pending": false,
        "is_rating_locked": false,
        "is_shown_in_index": true,
        "jpeg_file_size": 0,
        "jpeg_height": 5263,
        "jpeg_url": "https://files.yande.re/image/75bc28b71241ba3e1efadbfe571c429e/yande.re%201120480%20airando%20animal_ears%20asada_shino%20breasts%20bunny_ears%20bunny_girl%20nipples%20no_bra%20sinon%20sword_art_online.jpg",
        "jpeg_width": 3721,
        "last_commented_at": 0,
        "last_noted_at": 0,
        "md5": "75bc28b71241ba3e1efadbfe571c429e",
        "parent_id": 1120479,
        "preview_height": 150,
        "preview_url": "https://assets.yande.re/data/preview/75/bc/75bc28b71241ba3e1efadbfe571c429e.jpg",
        "preview_width": 106,
        "rating": "q",
        "sample_file_size": 212193,
        "sample_height": 1500,
        "sample_url": "https://files.yande.re/sample/75bc28b71241ba3e1efadbfe571c429e/yande.re%201120480%20sample%20airando%20animal_ears%20asada_shino%20breasts%20bunny_ears%20bunny_girl%20nipples%20no_bra%20sinon%20sword_art_online.jpg",
        "sample_width": 1061,
        "score": 26,
        "source": "https://i.pximg.net/img-original/img/2019/11/12/20/26/18/77783770_p1.jpg",
        "status": "active",
        "tags": "airando animal_ears asada_shino breasts bunny_ears bunny_girl nipples no_bra sinon sword_art_online",
        "updated_at": 1694810361,
        "width": 3721
    },
    {
        "actual_preview_height": 300,
        "actual_preview_width": 212,
        "approver_id": null,
        "author": "TagMeMeMe!",
        "change": 5670654,
        "created_at": 1694810346,
        "creator_id": 485578,
        "file_ext": "jpg",
        "file_size": 10835982,
        "file_url": "https://files.yande.re/image/41be7e904ef98ed41d4808e47da4b095/yande.re%201120479%20airando%20animal_ears%20asada_shino%20bunny_ears%20bunny_girl%20fishnets%20no_bra%20pantyhose%20sinon%20sword_art_online.jpg",
        "frames": [],
        "frames_pending": [],
        "frames_pending_string": "",
        "frames_string": "",
        "has_children": true,
        "height": 5263,
        "id": 1120479,
        "is_held": false,
        "is_note_locked": false,
        "is_pending": false,
        "is_rating_locked": false,
        "is_shown_in_index": true,
        "jpeg_file_size": 0,
        "jpeg_height": 5263,
        "jpeg_url": "https://files.yande.re/image/41be7e904ef98ed41d4808e47da4b095/yande.re%201120479%20airando%20animal_ears%20asada_shino%20bunny_ears%20bunny_girl%20fishnets%20no_bra%20pantyhose%20sinon%20sword_art_online.jpg",
        "jpeg_width": 3721,
        "last_commented_at": 0,
        "last_noted_at": 0,
        "md5": "41be7e904ef98ed41d4808e47da4b095",
        "parent_id": null,
        "preview_height": 150,
        "preview_url": "https://assets.yande.re/data/preview/41/be/41be7e904ef98ed41d4808e47da4b095.jpg",
        "preview_width": 106,
        "rating": "q",
        "sample_file_size": 419467,
        "sample_height": 1500,
        "sample_url": "https://files.yande.re/sample/41be7e904ef98ed41d4808e47da4b095/yande.re%201120479%20sample%20airando%20animal_ears%20asada_shino%20bunny_ears%20bunny_girl%20fishnets%20no_bra%20pantyhose%20sinon%20sword_art_online.jpg",
        "sample_width": 1061,
        "score": 18,
        "source": "https://i.pximg.net/img-original/img/2019/11/12/20/26/18/77783770_p0.jpg",
        "status": "active",
        "tags": "airando animal_ears asada_shino bunny_ears bunny_girl fishnets no_bra pantyhose sinon sword_art_online",
        "updated_at": 1694810347,
        "width": 3721
    },
    {
        "actual_preview_height": 300,
        "actual_preview_width": 212,
        "approver_id": null,
        "author": "TagMeMeMe!",
        "change": 5669961,
        "created_at": 1694809676,
        "creator_id": 485578,
        "file_ext": "jpg",
        "file_size": 571194,
        "file_url": "https://files.yande.re/image/845d1d68ce62813f8e3cf0919484b430/yande.re%201120477%20airando%20animal_ears%20asada_shino%20bunny_ears%20bunny_girl%20megane%20no_bra%20sword_art_online.jpg",
        "frames": [],
        "frames_pending": [],
        "frames_pending_string": "",
        "frames_string": "",
        "has_children": false,
        "height": 4096,
        "id": 1120477,
        "is_held": false,
        "is_note_locked": false,
        "is_pending": false,
        "is_rating_locked": false,
        "is_shown_in_index": true,
        "jpeg_file_size": 0,
        "jpeg_height": 4096,
        "jpeg_url": "https://files.yande.re/image/845d1d68ce62813f8e3cf0919484b430/yande.re%201120477%20airando%20animal_ears%20asada_shino%20bunny_ears%20bunny_girl%20megane%20no_bra%20sword_art_online.jpg",
        "jpeg_width": 2896,
        "last_commented_at": 0,
        "last_noted_at": 0,
        "md5": "845d1d68ce62813f8e3cf0919484b430",
        "parent_id": null,
        "preview_height": 150,
        "preview_url": "https://assets.yande.re/data/preview/84/5d/845d1d68ce62813f8e3cf0919484b430.jpg",
        "preview_width": 106,
        "rating": "q",
        "sample_file_size": 202844,
        "sample_height": 1500,
        "sample_url": "https://files.yande.re/sample/845d1d68ce62813f8e3cf0919484b430/yande.re%201120477%20sample%20airando%20animal_ears%20asada_shino%20bunny_ears%20bunny_girl%20megane%20no_bra%20sword_art_online.jpg",
        "sample_width": 1061,
        "score": 20,
        "source": "https://twitter.com/island_kossori/status/1693542755056918712",
        "status": "active",
        "tags": "airando animal_ears asada_shino bunny_ears bunny_girl megane no_bra sword_art_online",
        "updated_at": 1694809676,
        "width": 2896
    },
    {
        "actual_preview_height": 300,
        "actual_preview_width": 214,
        "approver_id": null,
        "author": "Mr_GT",
        "change": 5671840,
        "created_at": 1693541189,
        "creator_id": 25882,
        "file_ext": "jpg",
        "file_size": 16285811,
        "file_url": "https://files.yande.re/image/c1a0580b6f6e3556037ef5ddf1225138/yande.re%201117210%20animal_ears%20asada_shino%20cameltoe%20cosplay%20fate_grand_order%20halloween%20heels%20kawase_seiki%20mash_kyrielight%20megane%20sword_art_online%20tail%20thighhighs.jpg",
        "frames": [],
        "frames_pending": [],
        "frames_pending_string": "",
        "frames_string": "",
        "has_children": false,
        "height": 6475,
        "id": 1117210,
        "is_held": true,
        "is_note_locked": false,
        "is_pending": false,
        "is_rating_locked": false,
        "is_shown_in_index": false,
        "jpeg_file_size": 0,
        "jpeg_height": 6475,
        "jpeg_url": "https://files.yande.re/image/c1a0580b6f6e3556037ef5ddf1225138/yande.re%201117210%20animal_ears%20asada_shino%20cameltoe%20cosplay%20fate_grand_order%20halloween%20heels%20kawase_seiki%20mash_kyrielight%20megane%20sword_art_online%20tail%20thighhighs.jpg",
        "jpeg_width": 4625,
        "last_commented_at": 0,
        "last_noted_at": 0,
        "md5": "c1a0580b6f6e3556037ef5ddf1225138",
        "parent_id": 1117208,
        "preview_height": 150,
        "preview_url": "https://assets.yande.re/data/preview/c1/a0/c1a0580b6f6e3556037ef5ddf1225138.jpg",
        "preview_width": 107,
        "rating": "q",
        "sample_file_size": 391507,
        "sample_height": 1500,
        "sample_url": "https://files.yande.re/sample/c1a0580b6f6e3556037ef5ddf1225138/yande.re%201117210%20sample%20animal_ears%20asada_shino%20cameltoe%20cosplay%20fate_grand_order%20halloween%20heels%20kawase_seiki%20mash_kyrielight%20megane%20sword_art_online%20tail%20thighhighs.jpg",
        "sample_width": 1071,
        "score": 14,
        "source": "",
        "status": "active",
        "tags": "animal_ears asada_shino cameltoe cosplay fate/grand_order halloween heels kawase_seiki mash_kyrielight megane sword_art_online tail thighhighs",
        "updated_at": 1694930393,
        "width": 4625
    },
    {
        "actual_preview_height": 300,
        "actual_preview_width": 214,
        "approver_id": null,
        "author": "Mr_GT",
        "change": 5671836,
        "created_at": 1693541063,
        "creator_id": 25882,
        "file_ext": "jpg",
        "file_size": 16294140,
        "file_url": "https://files.yande.re/image/a459cba083a00c7d357c7ff847314653/yande.re%201117208%20animal_ears%20asada_shino%20cameltoe%20cosplay%20fate_grand_order%20halloween%20heels%20kawase_seiki%20mash_kyrielight%20sinon%20sword_art_online%20tail%20thighhighs.jpg",
        "frames": [],
        "frames_pending": [],
        "frames_pending_string": "",
        "frames_string": "",
        "has_children": true,
        "height": 6475,
        "id": 1117208,
        "is_held": false,
        "is_note_locked": false,
        "is_pending": false,
        "is_rating_locked": false,
        "is_shown_in_index": true,
        "jpeg_file_size": 0,
        "jpeg_height": 6475,
        "jpeg_url": "https://files.yande.re/image/a459cba083a00c7d357c7ff847314653/yande.re%201117208%20animal_ears%20asada_shino%20cameltoe%20cosplay%20fate_grand_order%20halloween%20heels%20kawase_seiki%20mash_kyrielight%20sinon%20sword_art_online%20tail%20thighhighs.jpg",
        "jpeg_width": 4625,
        "last_commented_at": 0,
        "last_noted_at": 0,
        "md5": "a459cba083a00c7d357c7ff847314653",
        "parent_id": null,
        "preview_height": 150,
        "preview_url": "https://assets.yande.re/data/preview/a4/59/a459cba083a00c7d357c7ff847314653.jpg",
        "preview_width": 107,
        "rating": "q",
        "sample_file_size": 393445,
        "sample_height": 1500,
        "sample_url": "https://files.yande.re/sample/a459cba083a00c7d357c7ff847314653/yande.re%201117208%20sample%20animal_ears%20asada_shino%20cameltoe%20cosplay%20fate_grand_order%20halloween%20heels%20kawase_seiki%20mash_kyrielight%20sinon%20sword_art_online%20tail%20thighhighs.jpg",
        "sample_width": 1071,
        "score": 30,
        "source": "",
        "status": "active",
        "tags": "animal_ears asada_shino cameltoe cosplay fate/grand_order halloween heels kawase_seiki mash_kyrielight sinon sword_art_online tail thighhighs",
        "updated_at": 1694918999,
        "width": 4625
    },
    {
        "actual_preview_height": 300,
        "actual_preview_width": 198,
        "approver_id": null,
        "author": "whitespace1",
        "change": 5647057,
        "created_at": 1693099024,
        "creator_id": 457203,
        "file_ext": "jpg",
        "file_size": 4651272,
        "file_url": "https://files.yande.re/image/945959e2407667d2163afa1b3a30542c/yande.re%201116012%20asuna_%28sword_art_online%29%20breasts%20nipples%20no_bra%20open_shirt%20pajama%20pantsu%20sebu_illust%20sword_art_online.jpg",
        "frames": [],
        "frames_pending": [],
        "frames_pending_string": "",
        "frames_string": "",
        "has_children": false,
        "height": 5000,
        "id": 1116012,
        "is_held": false,
        "is_note_locked": false,
        "is_pending": false,
        "is_rating_locked": false,
        "is_shown_in_index": false,
        "jpeg_file_size": 0,
        "jpeg_height": 5000,
        "jpeg_url": "https://files.yande.re/image/945959e2407667d2163afa1b3a30542c/yande.re%201116012%20asuna_%28sword_art_online%29%20breasts%20nipples%20no_bra%20open_shirt%20pajama%20pantsu%20sebu_illust%20sword_art_online.jpg",
        "jpeg_width": 3307,
        "last_commented_at": 0,
        "last_noted_at": 0,
        "md5": "945959e2407667d2163afa1b3a30542c",
        "parent_id": 1116010,
        "preview_height": 150,
        "preview_url": "https://assets.yande.re/data/preview/94/59/945959e2407667d2163afa1b3a30542c.jpg",
        "preview_width": 99,
        "rating": "q",
        "sample_file_size": 308077,
        "sample_height": 1500,
        "sample_url": "https://files.yande.re/sample/945959e2407667d2163afa1b3a30542c/yande.re%201116012%20sample%20asuna_%28sword_art_online%29%20breasts%20nipples%20no_bra%20open_shirt%20pajama%20pantsu%20sebu_illust%20sword_art_online.jpg",
        "sample_width": 992,
        "score": 20,
        "source": "",
        "status": "active",
        "tags": "asuna_(sword_art_online) breasts nipples no_bra open_shirt pajama pantsu sebu_illust sword_art_online",
        "updated_at": 1693099028,
        "width": 3307
    },
    {
        "actual_preview_height": 300,
        "actual_preview_width": 198,
        "approver_id": null,
        "author": "whitespace1",
        "change": 5646928,
        "created_at": 1693099008,
        "creator_id": 457203,
        "file_ext": "jpg",
        "file_size": 4691214,
        "file_url": "https://files.yande.re/image/a3c1f7fd6992629df277134ad182c87c/yande.re%201116011%20asuna_%28sword_art_online%29%20bra%20open_shirt%20pajama%20pantsu%20sebu_illust%20sword_art_online.jpg",
        "frames": [],
        "frames_pending": [],
        "frames_pending_string": "",
        "frames_string": "",
        "has_children": false,
        "height": 5000,
        "id": 1116011,
        "is_held": false,
        "is_note_locked": false,
        "is_pending": false,
        "is_rating_locked": false,
        "is_shown_in_index": false,
        "jpeg_file_size": 0,
        "jpeg_height": 5000,
        "jpeg_url": "https://files.yande.re/image/a3c1f7fd6992629df277134ad182c87c/yande.re%201116011%20asuna_%28sword_art_online%29%20bra%20open_shirt%20pajama%20pantsu%20sebu_illust%20sword_art_online.jpg",
        "jpeg_width": 3307,
        "last_commented_at": 0,
        "last_noted_at": 0,
        "md5": "a3c1f7fd6992629df277134ad182c87c",
        "parent_id": 1116010,
        "preview_height": 150,
        "preview_url": "https://assets.yande.re/data/preview/a3/c1/a3c1f7fd6992629df277134ad182c87c.jpg",
        "preview_width": 99,
        "rating": "q",
        "sample_file_size": 312526,
        "sample_height": 1500,
        "sample_url": "https://files.yande.re/sample/a3c1f7fd6992629df277134ad182c87c/yande.re%201116011%20sample%20asuna_%28sword_art_online%29%20bra%20open_shirt%20pajama%20pantsu%20sebu_illust%20sword_art_online.jpg",
        "sample_width": 992,
        "score": 18,
        "source": "",
        "status": "active",
        "tags": "asuna_(sword_art_online) bra open_shirt pajama pantsu sebu_illust sword_art_online",
        "updated_at": 1693099013,
        "width": 3307
    },
    {
        "actual_preview_height": 300,
        "actual_preview_width": 212,
        "approver_id": null,
        "author": "TagMeMeMe!",
        "change": 5642689,
        "created_at": 1692772573,
        "creator_id": 485578,
        "file_ext": "jpg",
        "file_size": 1375092,
        "file_url": "https://files.yande.re/image/276804b44832f202e14dcd7c9ade055c/yande.re%201115145%20airando%20asuna_%28sword_art_online%29%20bikini%20swimsuits%20sword_art_online.jpg",
        "frames": [],
        "frames_pending": [],
        "frames_pending_string": "",
        "frames_string": "",
        "has_children": false,
        "height": 2000,
        "id": 1115145,
        "is_held": false,
        "is_note_locked": false,
        "is_pending": false,
        "is_rating_locked": false,
        "is_shown_in_index": true,
        "jpeg_file_size": 0,
        "jpeg_height": 2000,
        "jpeg_url": "https://files.yande.re/image/276804b44832f202e14dcd7c9ade055c/yande.re%201115145%20airando%20asuna_%28sword_art_online%29%20bikini%20swimsuits%20sword_art_online.jpg",
        "jpeg_width": 1414,
        "last_commented_at": 0,
        "last_noted_at": 0,
        "md5": "276804b44832f202e14dcd7c9ade055c",
        "parent_id": null,
        "preview_height": 150,
        "preview_url": "https://assets.yande.re/data/preview/27/68/276804b44832f202e14dcd7c9ade055c.jpg",
        "preview_width": 106,
        "rating": "q",
        "sample_file_size": 232877,
        "sample_height": 1500,
        "sample_url": "https://files.yande.re/sample/276804b44832f202e14dcd7c9ade055c/yande.re%201115145%20sample%20airando%20asuna_%28sword_art_online%29%20bikini%20swimsuits%20sword_art_online.jpg",
        "sample_width": 1061,
        "score": 16,
        "source": "https://kakuredokoro.booth.pm/items/4443189",
        "status": "active",
        "tags": "airando asuna_(sword_art_online) bikini swimsuits sword_art_online",
        "updated_at": 1692772573,
        "width": 1414
    },
    {
        "actual_preview_height": 300,
        "actual_preview_width": 182,
        "approver_id": null,
        "author": "TagMeMeMe!",
        "change": 5670162,
        "created_at": 1691522418,
        "creator_id": 485578,
        "file_ext": "jpg",
        "file_size": 4244642,
        "file_url": "https://files.yande.re/image/d863512f65bae028ff9698381e3490c7/yande.re%201111490%20alfheim_online%20leafa%20narisu%20no_bra%20pointy_ears%20sword%20sword_art_online%20thighhighs%20wings.jpg",
        "frames": [],
        "frames_pending": [],
        "frames_pending_string": "",
        "frames_string": "",
        "has_children": false,
        "height": 3799,
        "id": 1111490,
        "is_held": false,
        "is_note_locked": false,
        "is_pending": false,
        "is_rating_locked": false,
        "is_shown_in_index": true,
        "jpeg_file_size": 0,
        "jpeg_height": 3799,
        "jpeg_url": "https://files.yande.re/image/d863512f65bae028ff9698381e3490c7/yande.re%201111490%20alfheim_online%20leafa%20narisu%20no_bra%20pointy_ears%20sword%20sword_art_online%20thighhighs%20wings.jpg",
        "jpeg_width": 2302,
        "last_commented_at": 0,
        "last_noted_at": 0,
        "md5": "d863512f65bae028ff9698381e3490c7",
        "parent_id": null,
        "preview_height": 150,
        "preview_url": "https://assets.yande.re/data/preview/d8/63/d863512f65bae028ff9698381e3490c7.jpg",
        "preview_width": 91,
        "rating": "q",
        "sample_file_size": 221646,
        "sample_height": 1500,
        "sample_url": "https://files.yande.re/sample/d863512f65bae028ff9698381e3490c7/yande.re%201111490%20sample%20alfheim_online%20leafa%20narisu%20no_bra%20pointy_ears%20sword%20sword_art_online%20thighhighs%20wings.jpg",
        "sample_width": 909,
        "score": 13,
        "source": "https://i.pximg.net/img-original/img/2021/07/26/16/56/18/91514089_p0.jpg",
        "status": "active",
        "tags": "alfheim_online leafa narisu no_bra pointy_ears sword sword_art_online thighhighs wings",
        "updated_at": 1691522418,
        "width": 2302
    },
    {
        "actual_preview_height": 212,
        "actual_preview_width": 300,
        "approver_id": null,
        "author": "hellkaiser",
        "change": 5549690,
        "created_at": 1685967495,
        "creator_id": 329256,
        "file_ext": "jpg",
        "file_size": 1880871,
        "file_url": "https://files.yande.re/image/a667e3b1fb30399e585851898985e50a/yande.re%201095085%20abec%20asuna_%28sword_art_online%29%20bathing%20bunbun%20censored%20kirito%20kizmel%20naked%20onsen%20pointy_ears%20sword_art_online%20wet.jpg",
        "frames": [],
        "frames_pending": [],
        "frames_pending_string": "",
        "frames_string": "",
        "has_children": false,
        "height": 2048,
        "id": 1095085,
        "is_held": false,
        "is_note_locked": false,
        "is_pending": false,
        "is_rating_locked": false,
        "is_shown_in_index": true,
        "jpeg_file_size": 0,
        "jpeg_height": 2048,
        "jpeg_url": "https://files.yande.re/image/a667e3b1fb30399e585851898985e50a/yande.re%201095085%20abec%20asuna_%28sword_art_online%29%20bathing%20bunbun%20censored%20kirito%20kizmel%20naked%20onsen%20pointy_ears%20sword_art_online%20wet.jpg",
        "jpeg_width": 2896,
        "last_commented_at": 0,
        "last_noted_at": 0,
        "md5": "a667e3b1fb30399e585851898985e50a",
        "parent_id": null,
        "preview_height": 106,
        "preview_url": "https://assets.yande.re/data/preview/a6/67/a667e3b1fb30399e585851898985e50a.jpg",
        "preview_width": 150,
        "rating": "q",
        "sample_file_size": 273576,
        "sample_height": 1061,
        "sample_url": "https://files.yande.re/sample/a667e3b1fb30399e585851898985e50a/yande.re%201095085%20sample%20abec%20asuna_%28sword_art_online%29%20bathing%20bunbun%20censored%20kirito%20kizmel%20naked%20onsen%20pointy_ears%20sword_art_online%20wet.jpg",
        "sample_width": 1500,
        "score": 24,
        "source": "",
        "status": "active",
        "tags": "abec asuna_(sword_art_online) bathing bunbun censored kirito kizmel naked onsen pointy_ears sword_art_online wet",
        "updated_at": 1688565603,
        "width": 2896
    }
]